random_encrypt/RandomEncrypt.py
random_encrypt/__init__.py
random_tool-1.0.2.dist-info/LICENSE
random_tool-1.0.2.dist-info/METADATA
random_tool-1.0.2.dist-info/WHEEL
random_tool-1.0.2.dist-info/top_level.txt
random_tool-1.0.2.dist-info/RECORD
