Metadata-Version: 2.1
Name: random_tool
Version: 1.0.2
Summary: encrypt basic openssl
Home-page: https://github.com/siburuxue
Author: zhang peng
Author-email: siburuxue@gmail.com
License: Apache-2.0 License
Platform: all
License-File: LICENSE
